cdk_dynamo_table_view/__init__.py
cdk_dynamo_table_view/py.typed
cdk_dynamo_table_view/_jsii/__init__.py
cdk_dynamo_table_view/_jsii/cdk-dynamo-table-viewer@0.2.488.jsii.tgz
cdk_dynamo_table_view-0.2.488.dist-info/LICENSE
cdk_dynamo_table_view-0.2.488.dist-info/METADATA
cdk_dynamo_table_view-0.2.488.dist-info/WHEEL
cdk_dynamo_table_view-0.2.488.dist-info/top_level.txt
cdk_dynamo_table_view-0.2.488.dist-info/RECORD
